[
  {
    "ContainingType": "ContactWebAPI.Controllers.DataController",
    "Method": "Get",
    "RelativePath": "api/Data",
    "HttpMethod": "GET",
    "IsController": true,
    "Order": 0,
    "Parameters": [],
    "ReturnTypes": [
      {
        "Type": "System.Collections.Generic.IEnumerable\u00601[[ContactWebAPI.Models.Contact, ContactWebAPI, Version=1.0.0.0, Culture=neutral, PublicKeyToken=null]]",
        "MediaTypes": [
          "text/plain",
          "application/json",
          "text/json"
        ],
        "StatusCode": 200
      }
    ]
  },
  {
    "ContainingType": "ContactWebAPI.Controllers.DataController",
    "Method": "Post",
    "RelativePath": "api/Data",
    "HttpMethod": "POST",
    "IsController": true,
    "Order": 0,
    "Parameters": [
      {
        "Name": "contact",
        "Type": "ContactWebAPI.Models.Contact",
        "IsRequired": true
      }
    ],
    "ReturnTypes": [
      {
        "Type": "System.Void",
        "MediaTypes": [],
        "StatusCode": 200
      }
    ]
  },
  {
    "ContainingType": "ContactWebAPI.Controllers.DataController",
    "Method": "GetOne",
    "RelativePath": "api/Data/{id}",
    "HttpMethod": "GET",
    "IsController": true,
    "Order": 0,
    "Parameters": [
      {
        "Name": "id",
        "Type": "System.Int32",
        "IsRequired": true
      }
    ],
    "ReturnTypes": [
      {
        "Type": "ContactWebAPI.Models.Contact",
        "MediaTypes": [
          "text/plain",
          "application/json",
          "text/json"
        ],
        "StatusCode": 200
      }
    ]
  },
  {
    "ContainingType": "ContactWebAPI.Controllers.DataController",
    "Method": "Put",
    "RelativePath": "api/Data/{id}",
    "HttpMethod": "PUT",
    "IsController": true,
    "Order": 0,
    "Parameters": [
      {
        "Name": "contact",
        "Type": "ContactWebAPI.Models.Contact",
        "IsRequired": true
      },
      {
        "Name": "id",
        "Type": "",
        "IsRequired": true
      }
    ],
    "ReturnTypes": [
      {
        "Type": "System.Void",
        "MediaTypes": [],
        "StatusCode": 200
      }
    ]
  },
  {
    "ContainingType": "ContactWebAPI.Controllers.DataController",
    "Method": "Delete",
    "RelativePath": "api/Data/{id}",
    "HttpMethod": "DELETE",
    "IsController": true,
    "Order": 0,
    "Parameters": [
      {
        "Name": "id",
        "Type": "System.Int32",
        "IsRequired": true
      }
    ],
    "ReturnTypes": [
      {
        "Type": "System.Void",
        "MediaTypes": [],
        "StatusCode": 200
      }
    ]
  },
  {
    "ContainingType": "ContactWebAPI.Controllers.UserController",
    "Method": "Login",
    "RelativePath": "api/User/login",
    "HttpMethod": "POST",
    "IsController": true,
    "Order": 0,
    "Parameters": [
      {
        "Name": "model",
        "Type": "ContactWebAPI.Models.UserLogin",
        "IsRequired": true
      }
    ],
    "ReturnTypes": []
  },
  {
    "ContainingType": "ContactWebAPI.Controllers.UserController",
    "Method": "LoginForWeb",
    "RelativePath": "api/User/loginforweb",
    "HttpMethod": "POST",
    "IsController": true,
    "Order": 0,
    "Parameters": [
      {
        "Name": "model",
        "Type": "ContactWebAPI.Models.UserLogin",
        "IsRequired": true
      }
    ],
    "ReturnTypes": []
  },
  {
    "ContainingType": "ContactWebAPI.Controllers.UserController",
    "Method": "Logout",
    "RelativePath": "api/User/logout",
    "HttpMethod": "POST",
    "IsController": true,
    "Order": 0,
    "Parameters": [],
    "ReturnTypes": []
  },
  {
    "ContainingType": "ContactWebAPI.Controllers.UserController",
    "Method": "Register",
    "RelativePath": "api/User/register",
    "HttpMethod": "POST",
    "IsController": true,
    "Order": 0,
    "Parameters": [
      {
        "Name": "model",
        "Type": "ContactWebAPI.Models.UserRegistration",
        "IsRequired": true
      }
    ],
    "ReturnTypes": []
  }
]